maccabee/__init__.py
maccabee/constants.py
maccabee/exceptions.py
maccabee/logging.py
maccabee/benchmarking/__init__.py
maccabee/benchmarking/benchmarking.py
maccabee/data/cpp.csv
maccabee/data/lalonde.csv
maccabee/data/external_data/.DS_Store
maccabee/data/external_data/collaborative_perinatal_project.csv
maccabee/data_analysis/__init__.py
maccabee/data_analysis/data_analysis.py
maccabee/data_analysis/data_metrics.py
maccabee/data_generation/__init__.py
maccabee/data_generation/data_generating_process.py
maccabee/data_generation/data_generating_process_sampler.py
maccabee/data_generation/generated_data_set.py
maccabee/data_generation/utils.py
maccabee/data_sources/__init__.py
maccabee/data_sources/data_source_builders.py
maccabee/data_sources/data_sources.py
maccabee/data_sources/utils.py
maccabee/examples/__init__.py
maccabee/examples/genmatch.py
maccabee/modeling/__init__.py
maccabee/modeling/models.py
maccabee/modeling/performance_metrics.py
maccabee/parameters/__init__.py
maccabee/parameters/default_parameter_specification.yml
maccabee/parameters/metric_level_parameter_specifications.yml
maccabee/parameters/parameter_schema.yml
maccabee/parameters/parameter_store.py
maccabee/parameters/parameter_store_builders.py
maccabee/parameters/utils.py
maccabee/utilities/__init__.py
maccabee/utilities/multiprocessing.py
maccabee/utilities/threading.py
maccabee-1.0.2.dist-info/LICENSE
maccabee-1.0.2.dist-info/METADATA
maccabee-1.0.2.dist-info/WHEEL
maccabee-1.0.2.dist-info/top_level.txt
maccabee-1.0.2.dist-info/RECORD
